llama_index/retrievers/bedrock/__init__.py
llama_index/retrievers/bedrock/base.py
llama_index_retrievers_bedrock-0.5.0.dist-info/METADATA
llama_index_retrievers_bedrock-0.5.0.dist-info/WHEEL
llama_index_retrievers_bedrock-0.5.0.dist-info/licenses/LICENSE
llama_index_retrievers_bedrock-0.5.0.dist-info/RECORD
