Metadata-Version: 2.4
Name: llama-index-retrievers-bedrock
Version: 0.5.0
Summary: llama-index retrievers bedrock integration
Author-email: Your Name <you@example.com>
License-Expression: MIT
License-File: LICENSE
Requires-Python: <4.0,>=3.9
Requires-Dist: aioboto3<11.0.0,>=10.1.0
Requires-Dist: llama-index-core<0.15,>=0.13.0
